{
  "mcp_name": "Sweden Farm Grants MCP",
  "jurisdiction": "SE",
  "build_date": "2026-04-04",
  "grants": 47,
  "grant_items": 83,
  "stacking_rules": 80,
  "application_guidance_steps": 69,
  "fts_entries": 130,
  "sources": [
    "jordbruksverket.se — Strategiska planen 2023-2027",
    "jordbruksverket.se — Investeringsstod for okad konkurrenskraft (unit costs, regional ceilings)",
    "jordbruksverket.se — Kvaveklivet (100 MSEK/year 2025-2027)",
    "jordbruksverket.se — Robust primarproduktion (150 MSEK 2025)",
    "jordbruksverket.se — Diversifiering till annat an jordbruk",
    "jordbruksverket.se — Foradling av jordbruksprodukter 2024-2027",
    "jordbruksverket.se — Startstod / Stod till unga jordbrukare",
    "jordbruksverket.se — Gardsstod 2026 (130-147 EUR/ha)",
    "jordbruksverket.se — Kompensationsstod (stodområde 1-12)",
    "jordbruksverket.se — Nationellt stod (Norrlandsstod) areas 1-5",
    "jordbruksverket.se — Ersattning for ekologisk produktion",
    "jordbruksverket.se — Djurvalfardsersattning mjolkkor / far",
    "jordbruksverket.se — Miljoersattning vallodling 2026 (54 EUR/ha)",
    "jordbruksverket.se — Miljoersattning betesmarker och slatterangar (1,850-7,000 SEK/ha)",
    "jordbruksverket.se — Miljoersattning skotsel vatmarker (4,000 SEK/ha + 2,000-4,000 markersattning)",
    "jordbruksverket.se — Ersattning fanggroda (147 EUR/ha), mellangroda (128 EUR/ha), varbearbetning (61-72 EUR/ha)",
    "jordbruksverket.se — Ersattning blommande aker (235-663 EUR/ha by zone)",
    "jordbruksverket.se — Ersattning precisionsjordbruk planering (20-41 EUR/ha)",
    "jordbruksverket.se — Miljoersattning skyddszoner (4,000 / 10,000 SEK/ha)",
    "jordbruksverket.se — Miljoersattning fabodar",
    "jordbruksverket.se — Vattenvardsatgarder / tvastegsdiken / vatmarker",
    "jordbruksverket.se — EIP-Agri innovationsprojekt (80 MSEK)",
    "jordbruksverket.se — Kompetensutveckling (120 MSEK)",
    "jordbruksverket.se — Samarbetsstod korta leveranskedjor / distribution mat (50 MSEK)",
    "jordbruksverket.se — Leader 2023-2027 (1,700 MSEK)",
    "jordbruksverket.se — Notkreatursstod (87-96 EUR/djurenhet)",
    "jordbruksverket.se — Kulturmiljoer renskotselomradet",
    "jordbruksverket.se — Samarbetsprojekt vaxtskydd / markhalsa",
    "pts.se — Bredbandsstod 2026 (800 MSEK)",
    "tillvaxtverket.se — Landsbygdsutveckling (400 MSEK) / service landsbygder / digitalisering",
    "naturvardsverket.se — Klimatklivet (65% klimatinvesteringsstod, 6 omgangar 2026)",
    "naturvardsverket.se — LONA vatmark (90%) / vandringsled + betesmark (20 MSEK 2026)",
    "skogsstyrelsen.se — Nokas (70%, max 13,000-40,000 SEK/ha, 10-ars underhall)",
    "lansstyrelsen.se — Regionala investeringsstod (30-40%)"
  ]
}